{
	"format_version": [
		1,
		1,
		0
	],
	"csdec:decreation": {
		"textures": "decreation",
		"sound": "stone"
	},
	"csdec:burger": {
		"textures": "burger",
		"sound": "wood"
	},
	"csdec:banana": {
		"textures": "banana",
		"sound": "cloth"
	},
	"csdec:bush": {
		"textures": "bush",
		"sound": "sweet_berry_bush"
	},
	"csdec:csdeclog": {
		"textures": "csdeclog",
		"sound": "wood"
	},
	"csdec:money": {
		"textures": "money",
		"sound": "cloth"
	},
	"csdec:paintbrush": {
		"textures": "paintbrush",
		"sound": "wood"
	},
	"csdec:stool": {
		"textures": "stool",
		"sound": "wood"
	},
	"csdec:blender": {
		"textures": "blender",
		"sound": "metal"
	},
	"csdec:bricks": {
		"textures": "bricks",
		"sound": "brick"
	},
	"csdec:fridge_bottom": {
		"textures": "fridge",
		"sound": "metal"
	},
	"csdec:fridge_top": {
		"textures": "fridge",
		"sound": "metal"
	},
	"csdec:notes": {
		"textures": "notes",
		"sound": "cloth"
	},
	"csdec:paper": {
		"textures": "paper",
		"sound": "cloth"
	},
	"csdec:pen": {
		"textures": "pen",
		"sound": "lodestone"
	},
	"csdec:soda": {
		"textures": "soda",
		"sound": "metal"
	},
	"csdec:sticks": {
		"textures": "sticks",
		"sound": "wood"
	}
}