{
	"format_version": [
		1,
		1,
		0
	],
	"csdec:decreation": {
		"textures": "decreation",
		"sound": "stone"
	},
	"csdec:burger": {
		"textures": "burger",
		"sound": "wood"
	},
	"csdec:banana": {
		"textures": "banana",
		"sound": "cloth"
	},
	"csdec:bush": {
		"textures": "bush",
		"sound": "sweet_berry_bush"
	},
	"csdec:csdeclog": {
		"textures": "csdeclog",
		"sound": "wood"
	},
	"csdec:money": {
		"textures": "money",
		"sound": "cloth"
	},
	"csdec:paintbrush": {
		"textures": "paintbrush",
		"sound": "wood"
	},
	"csdec:stool": {
		"textures": "stool",
		"sound": "wood"
	},
	"csdec:blender": {
		"textures": "blender",
		"sound": "metal"
	},
	"csdec:bricks": {
		"textures": "bricks",
		"sound": "brick"
	},
	"csdec:fridge_bottom": {
		"textures": "fridge",
		"sound": "metal"
	},
	"csdec:fridge_top": {
		"textures": "fridge",
		"sound": "metal"
	},
	"csdec:notes": {
		"textures": "notes",
		"sound": "cloth"
	},
	"csdec:paper": {
		"textures": "paper",
		"sound": "cloth"
	},
	"csdec:pen": {
		"textures": "pen",
		"sound": "lodestone"
	},
	"csdec:soda": {
		"textures": "soda",
		"sound": "metal"
	},
	"csdec:sticks": {
		"textures": "sticks",
		"sound": "wood"
	},
	"csdec:hockey": {
		"textures": "hockey",
		"sound": "lodestone"
	},
	"csdec:pong": {
		"textures": "pong",
		"sound": "lodestone"
	},
	"csdec:shower": {
		"textures": "shower",
		"sound": "metal"
	},
	"csdec:sink": {
		"textures": "sink",
		"sound": "metal"
	},
	"csdec:sinkoutdoor": {
		"textures": "sinkoutdoor",
		"sound": "metal"
	},
	"csdec:toilet": {
		"textures": "toilet",
		"sound": "metal"
	},
	"csdec:bedside": {
		"textures": "sinkoutdoor",
		"sound": "wood"
	},
	"csdec:books": {
		"textures": "sinkoutdoor",
		"sound": "cloth"
	},
	"csdec:soap": {
		"textures": "sinkoutdoor",
		"sound": "slime"
	},
	"csdec:rollfront": {
		"textures": "roll",
		"sound": "cloth"
	},
	"csdec:rollback": {
		"textures": "roll",
		"sound": "cloth"
	},
	"csdec:tv": {
		"textures": "tv",
		"sound": "lodestone"
	},
	"csdec:plastic_block": {
		"textures": "plastic",
		"sound": "lodestone"
	},
	"csdec:plastic_cut": {
		"textures": "plastic_cut",
		"sound": "lodestone"
	},
	"csdec:plastic_tiles": {
		"textures": "plastic_tiles",
		"sound": "lodestone"
	},
	"csdec:plastic_black_block": {
		"textures": "plastic_black",
		"sound": "lodestone"
	},
	"csdec:plastic_black_cut": {
		"textures": "plastic_black_cut",
		"sound": "lodestone"
	},
	"csdec:plastic_black_tiles": {
		"textures": "plastic_black_tiles",
		"sound": "lodestone"
	},
	"csdec:plastic_blue_block": {
		"textures": "plastic_blue",
		"sound": "lodestone"
	},
	"csdec:plastic_blue_cut": {
		"textures": "plastic_blue_cut",
		"sound": "lodestone"
	},
	"csdec:plastic_blue_tiles": {
		"textures": "plastic_blue_tiles",
		"sound": "lodestone"
	},
	"csdec:plastic_brown_block": {
		"textures": "plastic_brown",
		"sound": "lodestone"
	},
	"csdec:plastic_brown_cut": {
		"textures": "plastic_brown_cut",
		"sound": "lodestone"
	},
	"csdec:plastic_brown_tiles": {
		"textures": "plastic_brown_tiles",
		"sound": "lodestone"
	},
	"csdec:plastic_cyan_block": {
		"textures": "plastic_cyan",
		"sound": "lodestone"
	},
	"csdec:plastic_cyan_cut": {
		"textures": "plastic_cyan_cut",
		"sound": "lodestone"
	},
	"csdec:plastic_cyan_tiles": {
		"textures": "plastic_cyan_tiles",
		"sound": "lodestone"
	},
	"csdec:plastic_gray_block": {
		"textures": "plastic_gray",
		"sound": "lodestone"
	},
	"csdec:plastic_gray_cut": {
		"textures": "plastic_gray_cut",
		"sound": "lodestone"
	},
	"csdec:plastic_gray_tiles": {
		"textures": "plastic_gray_tiles",
		"sound": "lodestone"
	},
	"csdec:plastic_green_block": {
		"textures": "plastic_green",
		"sound": "lodestone"
	},
	"csdec:plastic_green_cut": {
		"textures": "plastic_green_cut",
		"sound": "lodestone"
	},
	"csdec:plastic_green_tiles": {
		"textures": "plastic_green_tiles",
		"sound": "lodestone"
	},
	"csdec:plastic_light_blue_block": {
		"textures": "plastic_light_blue",
		"sound": "lodestone"
	},
	"csdec:plastic_light_blue_cut": {
		"textures": "plastic_light_blue_cut",
		"sound": "lodestone"
	},
	"csdec:plastic_light_blue_tiles": {
		"textures": "plastic_light_blue_tiles",
		"sound": "lodestone"
	},
	"csdec:plastic_lime_block": {
		"textures": "plastic_lime",
		"sound": "lodestone"
	},
	"csdec:plastic_lime_cut": {
		"textures": "plastic_lime_cut",
		"sound": "lodestone"
	},
	"csdec:plastic_lime_tiles": {
		"textures": "plastic_lime_tiles",
		"sound": "lodestone"
	},
	"csdec:plastic_magenta_block": {
		"textures": "plastic_magenta",
		"sound": "lodestone"
	},
	"csdec:plastic_magenta_cut": {
		"textures": "plastic_magenta_cut",
		"sound": "lodestone"
	},
	"csdec:plastic_magenta_tiles": {
		"textures": "plastic_magenta_tiles",
		"sound": "lodestone"
	},
	"csdec:plastic_orange_block": {
		"textures": "plastic_orange",
		"sound": "lodestone"
	},
	"csdec:plastic_orange_cut": {
		"textures": "plastic_orange_cut",
		"sound": "lodestone"
	},
	"csdec:plastic_orange_tiles": {
		"textures": "plastic_orange_tiles",
		"sound": "lodestone"
	},
	"csdec:plastic_pink_block": {
		"textures": "plastic_pink",
		"sound": "lodestone"
	},
	"csdec:plastic_pink_cut": {
		"textures": "plastic_pink_cut",
		"sound": "lodestone"
	},
	"csdec:plastic_pink_tiles": {
		"textures": "plastic_pink_tiles",
		"sound": "lodestone"
	},
	"csdec:plastic_purple_block": {
		"textures": "plastic_purple",
		"sound": "lodestone"
	},
	"csdec:plastic_purple_cut": {
		"textures": "plastic_purple_cut",
		"sound": "lodestone"
	},
	"csdec:plastic_purple_tiles": {
		"textures": "plastic_purple_tiles",
		"sound": "lodestone"
	},
	"csdec:plastic_red_block": {
		"textures": "plastic_red",
		"sound": "lodestone"
	},
	"csdec:plastic_red_cut": {
		"textures": "plastic_red_cut",
		"sound": "lodestone"
	},
	"csdec:plastic_red_tiles": {
		"textures": "plastic_red_tiles",
		"sound": "lodestone"
	},
	"csdec:plastic_silver_block": {
		"textures": "plastic_silver",
		"sound": "lodestone"
	},
	"csdec:plastic_silver_cut": {
		"textures": "plastic_silver_cut",
		"sound": "lodestone"
	},
	"csdec:plastic_silver_tiles": {
		"textures": "plastic_silver_tiles",
		"sound": "lodestone"
	},
	"csdec:plastic_white_block": {
		"textures": "plastic_white",
		"sound": "lodestone"
	},
	"csdec:plastic_white_cut": {
		"textures": "plastic_white_cut",
		"sound": "lodestone"
	},
	"csdec:plastic_white_tiles": {
		"textures": "plastic_white_tiles",
		"sound": "lodestone"
	},
	"csdec:plastic_yellow_block": {
		"textures": "plastic_yellow",
		"sound": "lodestone"
	},
	"csdec:plastic_yellow_cut": {
		"textures": "plastic_yellow_cut",
		"sound": "lodestone"
	},
	"csdec:plastic_yellow_tiles": {
		"textures": "plastic_yellow_tiles",
		"sound": "lodestone"
	}
}